texture_color_segmentation/__init__.py
texture_color_segmentation/feature_extraction.py
texture_color_segmentation/utils.py
texture_color_segmentation/distance_regularized_level_set_evolution/__init__.py
texture_color_segmentation/distance_regularized_level_set_evolution/drlse_algo.py
texture_color_segmentation/distance_regularized_level_set_evolution/find_lsf.py
texture_color_segmentation/distance_regularized_level_set_evolution/potential_func.py
texture_color_segmentation-1.0.1.dist-info/METADATA
texture_color_segmentation-1.0.1.dist-info/WHEEL
texture_color_segmentation-1.0.1.dist-info/licenses/LICENSE.txt
texture_color_segmentation-1.0.1.dist-info/RECORD
