Metadata-Version: 2.3
Name: texture_color_segmentation
Version: 1.0.1
Summary: A Python package for image segmentation that combines texture features with color edges to create precise object boundaries.
Project-URL: Homepage, https://github.com/HuysArthur/texture-features-as-optimization-for-unsupervised-image-segmentation
Project-URL: Issues, https://github.com/HuysArthur/texture-features-as-optimization-for-unsupervised-image-segmentation/issues
Author: Arthur Huys
License-File: LICENSE.txt
Classifier: License :: OSI Approved :: MIT License
Classifier: Operating System :: OS Independent
Classifier: Programming Language :: Python :: 3
Requires-Python: >=3.8
Requires-Dist: matplotlib
Requires-Dist: opencv-python
Requires-Dist: pywavelets
Requires-Dist: scikit-image
Requires-Dist: scipy
